xfastertransformer/__init__.py
xfastertransformer/automodel.py
xfastertransformer/env.py
xfastertransformer/libiomp5.so
xfastertransformer/libxfastertransformer_pt.so
xfastertransformer/libxft_comm_helper.so
xfastertransformer/tools/__init__.py
xfastertransformer/tools/baichuan2_convert.py
xfastertransformer/tools/baichuan_convert.py
xfastertransformer/tools/chatglm2_convert.py
xfastertransformer/tools/chatglm3_convert.py
xfastertransformer/tools/chatglm4_convert.py
xfastertransformer/tools/chatglm_convert.py
xfastertransformer/tools/convert.py
xfastertransformer/tools/llama_convert.py
xfastertransformer/tools/opt_convert.py
xfastertransformer/tools/qwen2_convert.py
xfastertransformer/tools/qwen_convert.py
xfastertransformer/tools/yarn_llama_convert.py
xfastertransformer_icx-1.8.2.dist-info/LICENSE
xfastertransformer_icx-1.8.2.dist-info/METADATA
xfastertransformer_icx-1.8.2.dist-info/WHEEL
xfastertransformer_icx-1.8.2.dist-info/top_level.txt
xfastertransformer_icx-1.8.2.dist-info/RECORD
